particula/__init__.py
particula/abc_builder.py
particula/abc_factory.py
particula/aerosol.py
particula/aerosol_builder.py
particula/builder_mixin.py
particula/logger_setup.py
particula/runnable.py
particula/activity/__init__.py
particula/activity/activity_coefficients.py
particula/activity/bat_blending.py
particula/activity/bat_coefficients.py
particula/activity/convert_functional_group.py
particula/activity/gibbs.py
particula/activity/gibbs_mixing.py
particula/activity/phase_separation.py
particula/activity/ratio.py
particula/activity/water_activity.py
particula/activity/tests/activity_coefficients_test.py
particula/activity/tests/bat_blending_test.py
particula/activity/tests/convert_functional_group_test.py
particula/activity/tests/gibbs_mixing_test.py
particula/activity/tests/gibbs_test.py
particula/activity/tests/phase_separation_test.py
particula/activity/tests/ratio_test.py
particula/activity/tests/water_activity_test.py
particula/dynamics/__init__.py
particula/dynamics/dilution.py
particula/dynamics/particle_process.py
particula/dynamics/coagulation/__init__.py
particula/dynamics/coagulation/brownian_kernel.py
particula/dynamics/coagulation/charged_dimensional_kernel.py
particula/dynamics/coagulation/charged_dimensional_kernel.py.backup
particula/dynamics/coagulation/charged_dimensionless_kernel.py
particula/dynamics/coagulation/charged_kernel_strategy.py
particula/dynamics/coagulation/coagulation_factories.py
particula/dynamics/coagulation/coagulation_rate.py
particula/dynamics/coagulation/sedimentation_kernel.py
particula/dynamics/coagulation/turbulent_shear_kernel.py
particula/dynamics/coagulation/coagulation_builder/__init__.py
particula/dynamics/coagulation/coagulation_builder/brownian_coagulation_builder.py
particula/dynamics/coagulation/coagulation_builder/charged_coagulation_builder.py
particula/dynamics/coagulation/coagulation_builder/coagulation_builder_mixin.py
particula-0.2.10.dist-info/licenses/license
particula-0.2.10.dist-info/WHEEL
particula-0.2.10.dist-info/METADATA
particula-0.2.10.dist-info/RECORD
