Metadata-Version: 2.4
Name: particula
Version: 0.2.10
Summary: a simple, fast, and powerful particle simulator
Keywords: atmospheric,particles,climate,aerosol,particulate
Author-email: Particula developers <uncscode@users.noreply.github.com>
Requires-Python: >=3.9
Classifier: Programming Language :: Python :: 3
Classifier: Programming Language :: Python :: 3 :: Only
Classifier: License :: OSI Approved :: MIT License
Classifier: Intended Audience :: Science/Research
Classifier: Topic :: Scientific/Engineering :: Atmospheric Science
License-File: license
Requires-Dist: numpy>=2.0.0
Requires-Dist: scipy>=1.12
Requires-Dist: particula[dev] ; extra == "all"
Requires-Dist: particula[extra] ; extra == "all"
Requires-Dist: pylint ; extra == "dev"
Requires-Dist: pytest ; extra == "dev"
Requires-Dist: pytest-cov ; extra == "dev"
Requires-Dist: autopep8 ; extra == "dev"
Requires-Dist: jupyterlab ; extra == "dev"
Requires-Dist: typing ; extra == "dev"
Requires-Dist: build ; extra == "dev"
Requires-Dist: flake8 ; extra == "dev"
Requires-Dist: jupyter-book ; extra == "dev"
Requires-Dist: ghp-import ; extra == "dev"
Requires-Dist: mkdocs ; extra == "dev"
Requires-Dist: mkdocs-material[imaging] ; extra == "dev"
Requires-Dist: mkdocs-jupyter ; extra == "dev"
Requires-Dist: mkdocstrings[python] ; extra == "dev"
Requires-Dist: mkdocs-gen-files ; extra == "dev"
Requires-Dist: mkdocs-literate-nav ; extra == "dev"
Requires-Dist: griffe ; extra == "dev"
Requires-Dist: openai ; extra == "dev"
Requires-Dist: GitPython ; extra == "dev"
Requires-Dist: ruff ; extra == "dev"
Requires-Dist: mypy ; extra == "dev"
Requires-Dist: matplotlib ; extra == "extra"
Requires-Dist: pandas ; extra == "extra"
Requires-Dist: pint ; extra == "extra"
Requires-Dist: thermo ; extra == "extra"
Requires-Dist: tqdm ; extra == "extra"
Project-URL: homepage, https://github.com/uncscode/particula
Project-URL: repository, https://github.com/uncscode/particula
Provides-Extra: all
Provides-Extra: dev
Provides-Extra: extra
